<?xml version="1.0"?>
<opencv_storage>
<stage6>
  <maxWeakCount>28</maxWeakCount>
  <stageThreshold>-1.5304845571517944e+00</stageThreshold>
  <weakClassifiers>
    <_>
      <internalNodes>
        0 -1 1103 -18875521 -2623489 -863005701 -134217761 -78643201
        -1872897 -35651591 -570425669</internalNodes>
      <leafValues>
        -8.3069926500320435e-01 -4.2782151699066162e-01</leafValues></_>
    <_>
      <internalNodes>
        0 -1 3187 -1477767612 -570431677 -612459333 926087609
        -1370607674 -1742575021 -1720886083 -9025488</internalNodes>
      <leafValues>
        -5.5978834629058838e-01 -1.0801555216312408e-01</leafValues></_>
    <_>
      <internalNodes>
        0 -1 3761 261246260 -1898183689 -307372697 -1510703364 769600764
        665643918 251653341 150216444</internalNodes>
      <leafValues>
        -6.8946939706802368e-01 6.7338950932025909e-02</leafValues></_>
    <_>
      <internalNodes>
        0 -1 3346 -458331158 -1393760756 520115160 -1398997550 126449444
        451672841 2124246064 1553178007</internalNodes>
      <leafValues>
        -3.7978070974349976e-01 1.8190324306488037e-01</leafValues></_>
    <_>
      <internalNodes>
        0 -1 19 -1972702797 53394340 -827887954 1018701664 805139914
        233701372 30370486 800014916</internalNodes>
      <leafValues>
        -3.6023169755935669e-01 1.8892227113246918e-01</leafValues></_>
    <_>
      <internalNodes>
        0 -1 289 34545929 -1482672848 1541322994 -29197688 -545563703
        -1103644045 -262204316 -1509512676</internalNodes>
      <leafValues>
        -3.6020848155021667e-01 1.8319724500179291e-01</leafValues></_>
    <_>
      <internalNodes>
        0 -1 145 -1067571552 -2001625720 -1912938639 959299494
        2008178328 1022559692 46055669 -1363745381</internalNodes>
      <leafValues>
        -3.2996886968612671e-01 2.0170862972736359e-01</leafValues></_>
    <_>
      <internalNodes>
        0 -1 1663 1828091444 1278376672 -86677452 1660078201 49559863
        1299992740 1693529999 1728140360</internalNodes>
      <leafValues>
        -4.9745309352874756e-01 1.3964104652404785e-01</leafValues></_>
    <_>
      <internalNodes>
        0 -1 2686 -1908906144 1032650696 272517298 -1329891462
        1627155800 -1610716242 1590252917 45089312</internalNodes>
      <leafValues>
        -5.6677329540252686e-01 1.1057788133621216e-01</leafValues></_>
    <_>
      <internalNodes>
        0 -1 2999 -1100046617 -255958375 -46409740 -367785236 375388789
        1132279413 -1224812044 -1149320115</internalNodes>
      <leafValues>
        -2.9810032248497009e-01 2.2569391131401062e-01</leafValues></_>
    <_>
      <internalNodes>
        0 -1 3764 1006040981 -2132216328 433806622 32435645 -1091217519
        217894995 -1284022735 -125829277</internalNodes>
      <leafValues>
        -2.8458371758460999e-01 2.4338197708129883e-01</leafValues></_>
    <_>
      <internalNodes>
        0 -1 2471 1412265363 -705568214 904701907 500475725 -2022606456
        -1242103873 -815956100 -1146633287</internalNodes>
      <leafValues>
        -2.1336905658245087e-01 3.3216863870620728e-01</leafValues></_>
    <_>
      <internalNodes>
        0 -1 1351 -1568871866 -1270052460 -1656518686 75413429
        1181989800 -2047546935 -943341893 1248613446</internalNodes>
      <leafValues>
        -3.6651360988616943e-01 1.9098807871341705e-01</leafValues></_>
    <_>
      <internalNodes>
        0 -1 504 -2064979176 1829613843 -920809166 -1642242589
        1146452501 -1329747564 -1262092623 1142192022</internalNodes>
      <leafValues>
        -4.5525515079498291e-01 1.5071775019168854e-01</leafValues></_>
    <_>
      <internalNodes>
        0 -1 1007 -877670908 -1371579479 615291684 917243712 -1392899198
        -708853088 1983866348 -763996818</internalNodes>
      <leafValues>
        -3.5757175087928772e-01 1.9988474249839783e-01</leafValues></_>
    <_>
      <internalNodes>
        0 -1 2904 -16790019 -69554182 -673471819 1432874751 -1346424583
        -19615919 -320895310 -165696889</internalNodes>
      <leafValues>
        -1.6655236482620239e-01 4.4844248890876770e-01</leafValues></_>
    <_>
      <internalNodes>
        0 -1 1570 82450177 -1161624986 -862488059 -1261262008 339635318
        -39401560 2002333604 1076756736</internalNodes>
      <leafValues>
        -5.1265740394592285e-01 1.4817984402179718e-01</leafValues></_>
    <_>
      <internalNodes>
        0 -1 1909 -64916236 -1614930746 -1231236232 -841433890
        -823369990 -69402930 463865346 -70318609</internalNodes>
      <leafValues>
        -2.6519855856895447e-01 2.7005642652511597e-01</leafValues></_>
    <_>
      <internalNodes>
        0 -1 3054 1837881768 -12970124 -1365459188 -1598889696 711685706
        1895139522 777987652 549216324</internalNodes>
      <leafValues>
        -5.5129039287567139e-01 1.2879690527915955e-01</leafValues></_>
    <_>
      <internalNodes>
        0 -1 3779 198464607 -2022909042 -167781315 -1805851656
        2134895981 -1786966444 1070478309 148495832</internalNodes>
      <leafValues>
        -4.4132518768310547e-01 1.5572723746299744e-01</leafValues></_>
    <_>
      <internalNodes>
        0 -1 61 -14158349 1890812787 -1107410973 -134400093 -9052244
        656865135 -288505893 -373325173</internalNodes>
      <leafValues>
        -1.6843616962432861e-01 4.5373749732971191e-01</leafValues></_>
    <_>
      <internalNodes>
        0 -1 1727 -1225825280 -1604682314 1765493234 -1562061866
        -105332464 809365589 2067718408 275254480</internalNodes>
      <leafValues>
        -7.1084463596343994e-01 1.0987836867570877e-01</leafValues></_>
    <_>
      <internalNodes>
        0 -1 1634 1582967952 -36272992 1705747177 887719220 -472870432
        -2036266946 -1834265288 -1704025506</internalNodes>
      <leafValues>
        -3.1283745169639587e-01 2.2535613179206848e-01</leafValues></_>
    <_>
      <internalNodes>
        0 -1 2249 -865208243 922680764 872365999 1945386749 1470442205
        1035877245 -1631937825 -1643424865</internalNodes>
      <leafValues>
        -2.3456332087516785e-01 3.3114612102508545e-01</leafValues></_>
    <_>
      <internalNodes>
        0 -1 2828 574371328 -1371614836 -455131488 545790088 1059159923
        628878264 -1159000524 406735925</internalNodes>
      <leafValues>
        -6.9002878665924072e-01 1.0689466446638107e-01</leafValues></_>
    <_>
      <internalNodes>
        0 -1 1879 -1182243412 -1246446986 -636647146 1432168368
        474379096 -2111952178 447033979 -1735692109</internalNodes>
      <leafValues>
        -3.1827005743980408e-01 2.2951221466064453e-01</leafValues></_>
    <_>
      <internalNodes>
        0 -1 3262 1982292224 -1078611210 -1391054025 1068028666
        2020920102 -198220804 769630172 620385429</internalNodes>
      <leafValues>
        -4.1544932126998901e-01 1.8416941165924072e-01</leafValues></_>
    <_>
      <internalNodes>
        0 -1 750 393221264 384173948 1174488525 710690772 1060126268
        -1154547265 847525472 1303933972</internalNodes>
      <leafValues>
        -6.9612342119216919e-01 1.0404329746961594e-01</leafValues></_></weakClassifiers></stage6>
</opencv_storage>
